tiptoe/AzureSnowflakeHelper.py
tiptoe/__init__.py
tiptoe/__main__.py
tiptoe/localfiles.py
tiptoe/web.py
tiptoe-0.4.3.dist-info/LICENSE
tiptoe-0.4.3.dist-info/METADATA
tiptoe-0.4.3.dist-info/WHEEL
tiptoe-0.4.3.dist-info/top_level.txt
tiptoe-0.4.3.dist-info/RECORD
