Metadata-Version: 2.1
Name: tiptoe
Version: 0.4.3
Summary: A group of helpful tools for scrapping and automation
Home-page: https://github.com/jltipton/tiptoe
Author: Jason Tipton
Author-email: jasontipton@gmail.com
License: MIT
Platform: UNKNOWN
Classifier: Development Status :: 2 - Pre-Alpha
Classifier: License :: OSI Approved :: MIT License
Classifier: Programming Language :: Python
Classifier: Programming Language :: Python :: 3
Classifier: Programming Language :: Python :: 3.4
Classifier: Programming Language :: Python :: 3.5
Classifier: Programming Language :: Python :: 3.6
Classifier: Programming Language :: Python :: 3.7
